setup.py
compsim/__init__.py
compsim/company_name_similarity.py
compsim/company_score_tfidf.py
compsim.egg-info/PKG-INFO
compsim.egg-info/SOURCES.txt
compsim.egg-info/dependency_links.txt
compsim.egg-info/top_level.txt