Metadata-Version: 1.0
Name: compsim
Version: 0.0.3
Summary: Company Name Similarity Computer
Home-page: https://github.com/asamat/compsim
Author: Arunim Samat
Author-email: arunimsamat@gmail.com
License: MIT License
Platform: UNKNOWN
